tankoh2/__init__.py
tankoh2/__main__.py
tankoh2/abq_cae/__init__.py
tankoh2/abq_cae/continueVesselCAE.py
tankoh2/abq_cae/control_continueVesselCAE.py
tankoh2/arguments.py
tankoh2/control/__init__.py
tankoh2/control/control_cl.py
tankoh2/control/control_cryotank.py
tankoh2/control/control_doe.py
tankoh2/control/control_metal.py
tankoh2/control/control_winding.py
tankoh2/control/genericcontrol.py
tankoh2/control/settings_example.json
tankoh2/design/__init__.py
tankoh2/design/afp/__init__.py
tankoh2/design/afp/abqPyModules/__init__.py
tankoh2/design/afp/abqPyModules/abaqus_v6.env
tankoh2/design/afp/abqPyModules/abq_ODBDataExtraction.py
tankoh2/design/afp/abqPyModules/abq_functions.py
tankoh2/design/afp/abqPyModules/abq_variables.py
tankoh2/design/afp/abqPyModules/main360.py
tankoh2/design/afp/abqPyModules/utilities.py
tankoh2/design/afp/afpProcessClass.py
tankoh2/design/afp/afpProcessImplementations.py
tankoh2/design/afp/environment.yml
tankoh2/design/afp/gapVolumeContentFunction.py
tankoh2/design/afp/homLayUp.py
tankoh2/design/afp/importFromExcel.py
tankoh2/design/afp/inputFiles/ComplexCylinder.xlsx
tankoh2/design/afp/inputFiles/DemoCSTable.xlsx
tankoh2/design/afp/inputFiles/DemoStackingDefinition.xlsx
tankoh2/design/afp/inputFiles/OnlyDome.xlsx
tankoh2/design/afp/inputFiles/OnlyDomeAndClosed.xlsx
tankoh2/design/afp/inputFiles/OnlyIsoSteering.xlsx
tankoh2/design/afp/inputFiles/SteeringParametersV1.xlsx
tankoh2/design/afp/layUpClass.py
tankoh2/design/afp/mainAFP.py
tankoh2/design/afp/notIntegratedHelperModules/createIsotensoidDomeContour.py
tankoh2/design/afp/notIntegratedHelperModules/createTorisphericalDomeContour.py
tankoh2/design/afp/notIntegratedHelperModules/solveEquationsForMaterialMixingRules.py
tankoh2/design/afp/postProcessing.py
tankoh2/design/afp/postProcessingAbaqus.py
tankoh2/design/afp/postProcessingPython.py
tankoh2/design/afp/postProcessingResults.py
tankoh2/design/afp/saveVarForAbqPy.py
tankoh2/design/afp/workflowModules.py
tankoh2-2.9.0.dist-info/METADATA
tankoh2-2.9.0.dist-info/WHEEL
tankoh2-2.9.0.dist-info/licenses/LICENSE.md
tankoh2-2.9.0.dist-info/licenses/LICENSES/MIT.txt
tankoh2-2.9.0.dist-info/RECORD
