Metadata-Version: 2.4
Name: tankoh2
Version: 2.9.0
Summary: Design and optimization of H2 tanks for high pressure applications and cryogenic hydrogen storage
License-Expression: MIT
License-File: LICENSE.md
License-File: LICENSES/MIT.txt
Keywords: lh2 tank,winding,hydrogen,storage
Author: Sebastian Freund
Author-email: sebastian.freund@dlr.de>
Maintainer: Sebastian Freund
Maintainer-email: sebastian.freund@dlr.de>
Requires-Python: >=3.9,<4.0
Classifier: Programming Language :: Python :: 3
Classifier: Programming Language :: Python :: 3.9
Classifier: Programming Language :: Python :: 3.10
Classifier: Programming Language :: Python :: 3.11
Classifier: Programming Language :: Python :: 3.12
Classifier: Programming Language :: Python :: 3.13
Classifier: Programming Language :: Python :: 3.14
Requires-Dist: CoolProp
Requires-Dist: bokeh
Requires-Dist: defusedxml
Requires-Dist: matplotlib
Requires-Dist: numpy
Requires-Dist: openpyxl
Requires-Dist: openturns
Requires-Dist: pandas
Requires-Dist: patme
Requires-Dist: ruamel.yaml
Requires-Dist: scipy
Project-URL: Changelog, https://gitlab.dlr.de/sy-stm/software/tankoh2/-/blob/master/changelog.md
Project-URL: Documentation, https://sy-stm.pages.gitlab.dlr.de/software/tankoh2/
Project-URL: Homepage, https://gitlab.dlr.de/sy-stm/software//tankoh2
Project-URL: Repository, https://gitlab.com/DLR-SY/tank/tankoh2
